mpl_mollier_axes/__init__.py
mpl_mollier_axes/axes/MollierAxes.py
mpl_mollier_axes/axes/SkewYAxes.py
mpl_mollier_axes/axes/__init__.py
mpl_mollier_axes-0.1.0.post1.dist-info/LICENSE
mpl_mollier_axes-0.1.0.post1.dist-info/WHEEL
mpl_mollier_axes-0.1.0.post1.dist-info/METADATA
mpl_mollier_axes-0.1.0.post1.dist-info/RECORD
